{
  "success": true,
  "leaderboard": [
    {
      "rank": 1,
      "user_id": 6363051488,
      "username": "@Jeffnatius",
      "xp": 200,
      "level": 2
    },
    {
      "rank": 2,
      "user_id": 7105730933,
      "username": "@abiclighter",
      "xp": 142,
      "level": 1
    },
    {
      "rank": 3,
      "user_id": 6274470012,
      "username": "@levo100",
      "xp": 100,
      "level": 1
    },
    {
      "rank": 4,
      "user_id": 7611709300,
      "username": "@VanJohnovich",
      "xp": 80,
      "level": 0
    },
    {
      "rank": 5,
      "user_id": 1268008610,
      "username": "@Joybaeart",
      "xp": 76,
      "level": 0
    },
    {
      "rank": 6,
      "user_id": 8034369966,
      "username": "@Maito_is_great",
      "xp": 8,
      "level": 0
    },
    {
      "rank": 7,
      "user_id": 8099191714,
      "username": "@p00lboyq",
      "xp": 6,
      "level": 0
    },
    {
      "rank": 8,
      "user_id": 6523845740,
      "username": "@NiraNew",
      "xp": 5,
      "level": 0
    },
    {
      "rank": 9,
      "user_id": 1638084297,
      "username": "@IceFlurryX",
      "xp": 1,
      "level": 0
    },
    {
      "rank": 10,
      "user_id": 7020835758,
      "username": "@JJeremy11212",
      "xp": 1,
      "level": 0
    },
    {
      "rank": 11,
      "user_id": 7642527839,
      "username": "RonnyR",
      "xp": 1,
      "level": 0
    },
    {
      "rank": 12,
      "user_id": 8388484470,
      "username": "B",
      "xp": 1,
      "level": 0
    },
    {
      "rank": 13,
      "user_id": 100294326,
      "username": "@xXCHNGx",
      "xp": 0,
      "level": 0
    },
    {
      "rank": 14,
      "user_id": 977733309,
      "username": "@Loboszlai",
      "xp": 0,
      "level": 0
    },
    {
      "rank": 15,
      "user_id": 1189624171,
      "username": "@iiiMrMiii",
      "xp": 0,
      "level": 0
    },
    {
      "rank": 16,
      "user_id": 1442345871,
      "username": "@Leventtao2783",
      "xp": 0,
      "level": 0
    },
    {
      "rank": 17,
      "user_id": 1575936630,
      "username": "@ProfessorPepeXCalls",
      "xp": 0,
      "level": 0
    },
    {
      "rank": 18,
      "user_id": 1846091857,
      "username": "@@ahhshoot",
      "xp": 0,
      "level": 0
    },
    {
      "rank": 19,
      "user_id": 1920467037,
      "username": "@Se7enDigitsOrDie",
      "xp": 0,
      "level": 0
    },
    {
      "rank": 20,
      "user_id": 5073688855,
      "username": "@basedwojek",
      "xp": 0,
      "level": 0
    }
  ],
  "last_updated": "2026-04-06T02:08:19.625123",
  "total_users": 20
}